<?xml version="1.0" encoding="UTF-8"?>
<Date date="2016-06-20"><Message><Id>41736</Id><Msg>#ونفت یعنی واقعا حقوقی دلش میاد این صف فروش رو جمع نکنه امروز ؟ قرارداد با شرکت خارجی قطعی شده ؟ کی اعلام میشه ؟</Msg><Username>amirpr2006</Username><DateTime>2016-06-19 12:06:33.0</DateTime><Sentiment /></Message><Message><Id>41724</Id><Msg>#شپنا هر کی گوهران بخره رو دستش میمونه با چقد سودگوهران میتونید ضررهاتون روجبران کنید</Msg><Username>mj324</Username><DateTime>2016-06-19 12:08:04.0</DateTime><Sentiment>Sell</Sentiment></Message><Message><Id>41730</Id><Msg>#ونفت دوست عزیز شایعه چیه ؟ مثل خیلی سهم های دیگه اینم یه سهم . صورت های مالی رو هم گزارش داده که طبق گفته دوستان عالی بوده منظورتون چیه دقیقا ؟</Msg><Username>amirpr2006</Username><DateTime>2016-06-19 14:07:49.0</DateTime><Sentiment /></Message><Message><Id>41729</Id><Msg>#ونفت با توجه به خبری که هم اکنون به دستم رسید فردا شاهد صف خرید سنگین در نماد ونفت شرکت سرمایه گذاری نفت خواهیم بود ...</Msg><Username>venaft500petrol250</Username><DateTime>2016-06-19 17:11:53.0</DateTime><Sentiment>Buy</Sentiment></Message><Message><Id>41728</Id><Msg>#ونفت آقا امیر اگه خبری پشتش بود صف فروشش جمع میکردن یا ی حمایت میکردن.دوست عزیز اینم داشته باش ک من تک سهم ونفتم</Msg><Username>mo170</Username><DateTime>2016-06-19 17:22:39.0</DateTime><Sentiment /></Message><Message><Id>41727</Id><Msg>#ونفت خدا کنه صف فروش نباشه ما قبولش داریم</Msg><Username>mo170</Username><DateTime>2016-06-19 17:24:44.0</DateTime><Sentiment /></Message><Message><Id>41723</Id><Msg>این آمار افت و خیز پالایشیها از آذر 94 هستش که میتونه کمکشون کنه که با سهمشون چند چندن. #شاوان 574-1441-871 #شبندر 376-550-450 #شتران 205-390-257 #شبریز 286-621-365 #شپنا 191-354-269 .... آمار نشون...</Msg><Username>ahm80321</Username><DateTime>2016-06-19 19:56:15.0</DateTime><Sentiment /></Message><Message><Id>41726</Id><Msg>#خساپا #ذوب #وهور #شبندر #ونفت ...در بورس ایران مهم تر از این که کدام سهم بهتر است یا بدتر یا کدام سهم خبرهای خوبی داره مهم تر از اینا کدوم سهم بازیگران و سفته بازهای بهتری داره و کدوم سهم حقوقی و...</Msg><Username>amirpr2006</Username><DateTime>2016-06-19 21:23:41.0</DateTime><Sentiment /></Message></Date>
